lalalang/__init__.py
lalalang/__main__.py
lalalang/evaluator/__init__.py
lalalang/evaluator/builtins.py
lalalang/evaluator/environment.py
lalalang/evaluator/evaluator.py
lalalang/evaluator/object.py
lalalang/lexer/__init__.py
lalalang/lexer/lexer.py
lalalang/lexer/token.py
lalalang/parser/__init__.py
lalalang/parser/ast.py
lalalang/parser/nodes.py
lalalang/parser/parser.py
lalalang/parser/precedence.py
tests/__init__.py
tests/test_evaluator.py
tests/test_lexer.py
tests/test_parser.py
tests/mocks/__init__.py
tests/mocks/evaluator.py
tests/mocks/lexer.py
tests/mocks/parser.py
lalalang-1.2.13.dist-info/LICENSE
lalalang-1.2.13.dist-info/METADATA
lalalang-1.2.13.dist-info/WHEEL
lalalang-1.2.13.dist-info/entry_points.txt
lalalang-1.2.13.dist-info/top_level.txt
lalalang-1.2.13.dist-info/RECORD
