Metadata-Version: 2.1
Name: lalalang
Version: 1.2.13
Summary: A programming language with a funny name
Home-page: https://github.com/manoloesparta/lalalang
Author: Manuel Esparza
License: MIT
Platform: UNKNOWN
Requires-Python: >=3.9
License-File: LICENSE
Requires-Dist: click (==8.0.1)
